mbed_devices/__init__.py
mbed_devices/__main__.py
mbed_devices/_version.py
mbed_devices/device.py
mbed_devices/exceptions.py
mbed_devices/mbed_devices.py
mbed_devices/mbed_tools.py
mbed_devices/_internal/__init__.py
mbed_devices/_internal/base_detector.py
mbed_devices/_internal/candidate_device.py
mbed_devices/_internal/detect_candidate_devices.py
mbed_devices/_internal/exceptions.py
mbed_devices/_internal/htm_file.py
mbed_devices/_internal/resolve_board.py
mbed_devices/_internal/darwin/__init__.py
mbed_devices/_internal/darwin/device_detector.py
mbed_devices/_internal/darwin/diskutil.py
mbed_devices/_internal/darwin/ioreg.py
mbed_devices/_internal/darwin/system_profiler.py
mbed_devices/_internal/linux/__init__.py
mbed_devices/_internal/linux/device_detector.py
mbed_devices/_internal/mbed_tools/__init__.py
mbed_devices/_internal/mbed_tools/list_connected_devices.py
mbed_devices/_internal/utils/__init__.py
mbed_devices/_internal/utils/python_helpers.py
mbed_devices/_internal/windows/__init__.py
mbed_devices/_internal/windows/component_descriptor.py
mbed_devices/_internal/windows/component_descriptor_utils.py
mbed_devices/_internal/windows/device_detector.py
mbed_devices/_internal/windows/device_instance_id.py
mbed_devices/_internal/windows/disk_aggregation.py
mbed_devices/_internal/windows/disk_drive.py
mbed_devices/_internal/windows/disk_partition.py
mbed_devices/_internal/windows/disk_partition_logical_disk_relationships.py
mbed_devices/_internal/windows/logical_disk.py
mbed_devices/_internal/windows/serial_port.py
mbed_devices/_internal/windows/serial_port_data_loader.py
mbed_devices/_internal/windows/system_data_loader.py
mbed_devices/_internal/windows/usb_controller.py
mbed_devices/_internal/windows/usb_data_aggregation.py
mbed_devices/_internal/windows/usb_device_identifier.py
mbed_devices/_internal/windows/usb_hub.py
mbed_devices/_internal/windows/usb_hub_data_loader.py
mbed_devices/_internal/windows/volume_set.py
mbed_devices-1.0.0.dist-info/LICENSE
mbed_devices-1.0.0.dist-info/METADATA
mbed_devices-1.0.0.dist-info/WHEEL
mbed_devices-1.0.0.dist-info/top_level.txt
mbed_devices-1.0.0.dist-info/RECORD
