Metadata-Version: 2.1
Name: mbed-devices
Version: 1.0.0
Summary: This package allows to list Mbed OS devices which are connected to the host computer.
Home-page: https://github.com/ARMmbed/mbed-devices
Author: Mbed team
Author-email: support@mbed.com
License: Apache 2.0
Keywords: Arm Mbed OS MbedOS devices list
Platform: UNKNOWN
Classifier: Development Status :: 3 - Alpha
Classifier: Intended Audience :: Developers
Classifier: License :: OSI Approved :: Apache Software License
Classifier: Programming Language :: Python
Classifier: Programming Language :: Python :: 3 :: Only
Classifier: Programming Language :: Python :: 3.6
Classifier: Programming Language :: Python :: 3.7
Classifier: Programming Language :: Python :: 3.8
Classifier: Topic :: Software Development :: Build Tools
Classifier: Topic :: Software Development :: Embedded Systems
Requires-Python: >=3.6,<4
Requires-Dist: python-dotenv
Requires-Dist: Click (==7.0)
Requires-Dist: mbed-targets (~=1.0)
Requires-Dist: mbed-tools-lib (~=1.2)
Requires-Dist: typing-extensions
Requires-Dist: tabulate
Requires-Dist: psutil ; platform_system == "Linux"
Requires-Dist: pyudev ; platform_system == "Linux"
Requires-Dist: pywin32 ; platform_system == "Windows"
Requires-Dist: dataclasses ; python_version < "3.7"
